aprsd_sentry_plugin/__init__.py
aprsd_sentry_plugin/sentry.py
aprsd_sentry_plugin-0.1.2.dist-info/LICENSE
aprsd_sentry_plugin-0.1.2.dist-info/METADATA
aprsd_sentry_plugin-0.1.2.dist-info/WHEEL
aprsd_sentry_plugin-0.1.2.dist-info/pbr.json
aprsd_sentry_plugin-0.1.2.dist-info/top_level.txt
aprsd_sentry_plugin-0.1.2.dist-info/RECORD
