Metadata-Version: 2.1
Name: aprsd-sentry-plugin
Version: 0.1.2
Summary: Ham radio APRSD plugin that does....
Author: Walter A. Boring IC
Author-email: waboring@hemna.com
License: Apache-2.0
Classifier: Topic :: Communications :: Ham Radio
Classifier: Operating System :: POSIX :: Linux
Classifier: Programming Language :: Python
Classifier: Programming Language :: Python :: 3.7
Classifier: Programming Language :: Python :: 3.8
Classifier: Programming Language :: Python :: 3.9
License-File: LICENSE
Requires-Dist: pbr
Requires-Dist: aprsd (>=2.5.0)
Requires-Dist: sentry-sdk
Requires-Dist: blinker
